aioslsk/__init__.py
aioslsk/base_manager.py
aioslsk/client.py
aioslsk/commands.py
aioslsk/constants.py
aioslsk/distributed.py
aioslsk/events.py
aioslsk/exceptions.py
aioslsk/interest/__init__.py
aioslsk/interest/manager.py
aioslsk/log_utils.py
aioslsk/naming.py
aioslsk/network/__init__.py
aioslsk/network/connection.py
aioslsk/network/network.py
aioslsk/network/rate_limiter.py
aioslsk/network/upnp.py
aioslsk/peer.py
aioslsk/protocol/__init__.py
aioslsk/protocol/messages.py
aioslsk/protocol/obfuscation.py
aioslsk/protocol/primitives.py
aioslsk/room/manager.py
aioslsk/room/model.py
aioslsk/search/__init__.py
aioslsk/search/manager.py
aioslsk/search/model.py
aioslsk/server.py
aioslsk/session.py
aioslsk/settings.py
aioslsk/shares/__init__.py
aioslsk/shares/cache.py
aioslsk/shares/manager.py
aioslsk/shares/model.py
aioslsk/shares/utils.py
aioslsk/tasks.py
aioslsk/transfer/__init__.py
aioslsk/transfer/cache.py
aioslsk/transfer/interface.py
aioslsk/transfer/manager.py
aioslsk/transfer/model.py
aioslsk/transfer/state.py
aioslsk/user/__init__.py
aioslsk/user/manager.py
aioslsk/user/model.py
aioslsk/utils.py
aioslsk-1.6.3.dist-info/METADATA
aioslsk-1.6.3.dist-info/WHEEL
aioslsk-1.6.3.dist-info/licenses/LICENSE
aioslsk-1.6.3.dist-info/RECORD
