Metadata-Version: 2.4
Name: aioslsk
Version: 1.6.3
Summary: Asyncio based SoulSeek client
License: GPL-3.0-or-later
License-File: LICENSE
Keywords: soulseek,p2p,async
Author: JurgenR
Author-email: 1249228+JurgenR@users.noreply.github.com
Requires-Python: >=3.10,<3.15
Classifier: Development Status :: 4 - Beta
Classifier: License :: OSI Approved :: GNU General Public License v3 or later (GPLv3+)
Classifier: Programming Language :: Python :: 3
Classifier: Programming Language :: Python :: 3.10
Classifier: Programming Language :: Python :: 3.11
Classifier: Programming Language :: Python :: 3.12
Classifier: Programming Language :: Python :: 3.13
Classifier: Programming Language :: Python :: 3.14
Classifier: Topic :: Communications :: File Sharing
Requires-Dist: aiofiles (>=22.1,<26.0)
Requires-Dist: async-timeout (>=4.0.3,<6.0.0)
Requires-Dist: async-upnp-client (>=0.33,<0.47)
Requires-Dist: multidict (>=6.0.5,<7.0.0)
Requires-Dist: mutagen (>=1.47.0,<2.0.0)
Requires-Dist: pydantic (>=2.12.0,<3.0.0)
Requires-Dist: pydantic-settings (>=2.4.0,<3.0.0)
Requires-Dist: types-aiofiles (>=23.2,<26.0)
Requires-Dist: typing-extensions (>=4.12.2,<5.0.0)
Project-URL: Documentation, https://readthedocs.org/projects/aioslsk/
Project-URL: Repository, https://github.com/JurgenR/aioslsk/
